mothree/__init__.py
mothree/py.typed
mothree/static/widget.bundle.js
mothree/static/widget.css
mothree/static/widget.js
mothree-0.1.0.dist-info/METADATA
mothree-0.1.0.dist-info/WHEEL
mothree-0.1.0.dist-info/RECORD
