Metadata-Version: 2.4
Name: mothree
Version: 0.1.0
Summary: Add your description here
Author-email: "Vincent D. Warmerdam" <vincentwarmerdam@gmail.com>
Requires-Python: >=3.13
Requires-Dist: anywidget>=0.9.18
